esterdb/__about__.py
esterdb/__init__.py
esterdb/_env.py
esterdb/main.py
esterdb-0.4.3.dist-info/METADATA
esterdb-0.4.3.dist-info/WHEEL
esterdb-0.4.3.dist-info/licenses/LICENSE.txt
esterdb-0.4.3.dist-info/RECORD
